Workbook

Sheet Products
A1: PRODUCTS
A2: # | B2: Product Name | C2: Price
A3: 1 | B3: Iron | C3: 7656
A4: 2 | B4: Blender | C4: 10780
A5: 3 | B5: Microwave Oven | C5: 30325
A6: 4 | B6: Air Fryer | C6: 18980
A7: 5 | B7: Infrared Cooker | C7: 14604
A8: 6 | B8: Sandwich Maker | C8: 8800
A9: 7 | B9: Refrigerator | C9: 113400

Sheet Report
A1: SALES REPORT
B2: Discount: | C2: 0.05
A3: # | B3: Student Name | C3: Product | D3: Price For 1 Product | E3: Quantity | F3: Price | G3: Discount Applied | H3: Final Price | I3: Tax (13%)
A4: 1 | B4: Abdul Rehman | C4: Sandwich Maker | D4: =VLOOKUP(C4,Products!$B$3:$C$9,2,FALSE) -> 8800 | E4: 5 | F4: =D4*E4 -> 44000 | G4: =F4*$C$2 -> 2200 | H4: =F4-G4 -> 41800 | I4: =IF(H4>=50000,(H4+(H4*0.13)),H4) -> 41800
A5: 2 | B5: Muhammad Yahya | C5: Refrigerator | D5: =VLOOKUP(C5,Products!$B$3:$C$9,2,FALSE) -> 113400 | E5: 2 | F5: =D5*E5 -> 226800 | G5: =F5*$C$2 -> 11340 | H5: =F5-G5 -> 215460 | I5: =IF(H5>=50000,(H5+(H5*0.13)),H5) -> 243469.8
A6: 3 | B6: Abdul Rafay | C6: Air Fryer | D6: =VLOOKUP(C6,Products!$B$3:$C$9,2,FALSE) -> 18980 | E6: 3 | F6: =D6*E6 -> 56940 | G6: =F6*$C$2 -> 2847 | H6: =F6-G6 -> 54093 | I6: =IF(H6>=50000,(H6+(H6*0.13)),H6) -> 61125.09
A7: 4 | B7: Abdul Sattar | C7: Sandwich Maker | D7: =VLOOKUP(C7,Products!$B$3:$C$9,2,FALSE) -> 8800 | E7: 6 | F7: =D7*E7 -> 52800 | G7: =F7*$C$2 -> 2640 | H7: =F7-G7 -> 50160 | I7: =IF(H7>=50000,(H7+(H7*0.13)),H7) -> 56680.8
A8: 5 | B8: Rayyan | C8: Air Fryer | D8: =VLOOKUP(C8,Products!$B$3:$C$9,2,FALSE) -> 18980 | E8: 1 | F8: =D8*E8 -> 18980 | G8: =F8*$C$2 -> 949 | H8: =F8-G8 -> 18031 | I8: =IF(H8>=50000,(H8+(H8*0.13)),H8) -> 18031
A9: 6 | B9: Hamza | C9: Blender | D9: =VLOOKUP(C9,Products!$B$3:$C$9,2,FALSE) -> 10780 | E9: 4 | F9: =D9*E9 -> 43120 | G9: =F9*$C$2 -> 2156 | H9: =F9-G9 -> 40964 | I9: =IF(H9>=50000,(H9+(H9*0.13)),H9) -> 40964
A10: 7 | B10: Asim | C10: Air Fryer | D10: =VLOOKUP(C10,Products!$B$3:$C$9,2,FALSE) -> 18980 | E10: 5 | F10: =D10*E10 -> 94900 | G10: =F10*$C$2 -> 4745 | H10: =F10-G10 -> 90155 | I10: =IF(H10>=50000,(H10+(H10*0.13)),H10) -> 101875.15
A11: 8 | B11: Siddiq | C11: Sandwich Maker | D11: =VLOOKUP(C11,Products!$B$3:$C$9,2,FALSE) -> 8800 | E11: 3 | F11: =D11*E11 -> 26400 | G11: =F11*$C$2 -> 1320 | H11: =F11-G11 -> 25080 | I11: =IF(H11>=50000,(H11+(H11*0.13)),H11) -> 25080
A12: 9 | B12: Anas Junaid | C12: Infrared Cooker | D12: =VLOOKUP(C12,Products!$B$3:$C$9,2,FALSE) -> 14604 | E12: 6 | F12: =D12*E12 -> 87624 | G12: =F12*$C$2 -> 4381.2 | H12: =F12-G12 -> 83242.8 | I12: =IF(H12>=50000,(H12+(H12*0.13)),H12) -> 94064.364
A13: 10 | B13: Zohaib | C13: Blender | D13: =VLOOKUP(C13,Products!$B$3:$C$9,2,FALSE) -> 10780 | E13: 1 | F13: =D13*E13 -> 10780 | G13: =F13*$C$2 -> 539 | H13: =F13-G13 -> 10241 | I13: =IF(H13>=50000,(H13+(H13*0.13)),H13) -> 10241
A14: 11 | B14: Hammad | C14: Sandwich Maker | D14: =VLOOKUP(C14,Products!$B$3:$C$9,2,FALSE) -> 8800 | E14: 4 | F14: =D14*E14 -> 35200 | G14: =F14*$C$2 -> 1760 | H14: =F14-G14 -> 33440 | I14: =IF(H14>=50000,(H14+(H14*0.13)),H14) -> 33440
A15: 12 | B15: Zarah | C15: Microwave Oven | D15: =VLOOKUP(C15,Products!$B$3:$C$9,2,FALSE) -> 30325 | E15: 5 | F15: =D15*E15 -> 151625 | G15: =F15*$C$2 -> 7581.25 | H15: =F15-G15 -> 144043.75 | I15: =IF(H15>=50000,(H15+(H15*0.13)),H15) -> 162769.44
... A21: 18 | B21: Muhammad Yahya | C21: Iron | D21: =VLOOKUP(C21,Products!$B$3:$C$9,2,FALSE) -> 7656 | E21: 1 | F21: =D21*E21 -> 7656 | G21: =F21*$C$2 -> 382.8 | H21: =F21-G21 -> 7273.2 | I21: =IF(H21>=50000,(H21+(H21*0.13)),H21) -> 7273.2
